primitive/__about__.py
primitive/__init__.py
primitive/cli.py
primitive/client.py
primitive/agent/__init__.py
primitive/agent/actions.py
primitive/agent/commands.py
primitive/agent/pxe.py
primitive/agent/runner.py
primitive/agent/uploader.py
primitive/auth/__init__.py
primitive/auth/actions.py
primitive/auth/commands.py
primitive/auth/graphql/__init__.py
primitive/auth/graphql/mutations.py
primitive/auth/graphql/queries.py
primitive/daemons/__init__.py
primitive/daemons/actions.py
primitive/daemons/commands.py
primitive/daemons/launch_agents.py
primitive/daemons/launch_service.py
primitive/daemons/ui.py
primitive/exec/__init__.py
primitive/exec/actions.py
primitive/exec/commands.py
primitive/exec/interactive.py
primitive/files/__init__.py
primitive/files/actions.py
primitive/files/commands.py
primitive/files/ui.py
primitive/files/graphql/__init__.py
primitive/files/graphql/fragments.py
primitive/files/graphql/mutations.py
primitive/files/graphql/queries.py
primitive/git/__init__.py
primitive/git/actions.py
primitive/git/commands.py
primitive/git/graphql/__init__.py
primitive/git/graphql/queries.py
primitive/graphql/__init__.py
primitive/graphql/relay.py
primitive/graphql/sdk.py
primitive/graphql/utility_fragments.py
primitive/hardware/__init__.py
primitive/hardware/actions.py
primitive/hardware/android.py
primitive/hardware/commands.py
primitive/hardware/ui.py
primitive/hardware/gpu/__init__.py
primitive/hardware/gpu/actions.py
primitive/hardware/gpu/apple.py
primitive/hardware/gpu/base.py
primitive/hardware/gpu/nvidia.py
primitive/hardware/graphql/__init__.py
primitive/hardware/graphql/fragments.py
primitive/hardware/graphql/mutations.py
primitive/hardware/graphql/queries.py
primitive/jobs/__init__.py
primitive/jobs/actions.py
primitive/jobs/commands.py
primitive/jobs/graphql/__init__.py
primitive/jobs/graphql/fragments.py
primitive/jobs/graphql/mutations.py
primitive/jobs/graphql/queries.py
primitive/messaging/__init__.py
primitive/messaging/actions.py
primitive-0.2.115.dist-info/METADATA
primitive-0.2.115.dist-info/WHEEL
primitive-0.2.115.dist-info/entry_points.txt
primitive-0.2.115.dist-info/licenses/LICENSE.txt
primitive-0.2.115.dist-info/RECORD
