Metadata-Version: 2.4
Name: primitive
Version: 0.2.115
Project-URL: Documentation, https://github.com//primitivecorp/primitive-cli#readme
Project-URL: Issues, https://github.com//primitivecorp/primitive-cli/issues
Project-URL: Source, https://github.com//primitivecorp/primitive-cli
Author-email: Dylan Stein <dylan@primitive.tech>, Chase Zimmerman <chase@primitive.tech>
License-Expression: MIT
License-File: LICENSE.txt
Classifier: Development Status :: 4 - Beta
Classifier: Programming Language :: Python
Classifier: Programming Language :: Python :: 3
Classifier: Programming Language :: Python :: 3.8
Classifier: Programming Language :: Python :: 3.9
Classifier: Programming Language :: Python :: 3.10
Classifier: Programming Language :: Python :: 3.11
Classifier: Programming Language :: Python :: 3.12
Classifier: Programming Language :: Python :: Implementation :: CPython
Classifier: Programming Language :: Python :: Implementation :: PyPy
Requires-Python: >=3.11
Requires-Dist: click==8.3.1
Requires-Dist: django>=5.2.8
Requires-Dist: gql[all]==3.5.3
Requires-Dist: ipython>=9.2.0
Requires-Dist: loguru==0.7.3
Requires-Dist: paramiko==4.0.0
Requires-Dist: pika==1.3.2
Requires-Dist: psutil==7.1.3
Requires-Dist: pyserial==3.5
Requires-Dist: rich==14.2.0
Requires-Dist: speedtest-cli==2.1.3
